fttp/__init__.py
fttp-0.0.1.dist-info/WHEEL
fttp-0.0.1.dist-info/METADATA
fttp-0.0.1.dist-info/RECORD
