Metadata-Version: 2.1
Name: fttp
Version: 0.0.1
Summary: Financial Trading Tools Project
Author: Artem Melnykov
Author-email: melnykov.artem.v@gmail.com
Requires-Python: >=3.9,<4.0
Classifier: Programming Language :: Python :: 3
Classifier: Programming Language :: Python :: 3.9
